{"_id":53,"W":"ph","_mtype":0,"_contins":11,"_lock":0,"_metalock":0,"_labels":[23,14,2],"_sources":[["player21","KGS+ Lecture 05.06.2010","Alexandre Dinerchtein"]],"C":"Not really Joseki anymore, because Black&#39;s corner is too good compared to what White can get out of his wall.","_lang":"en","_alllangs":["en"],"_talkCount":"1","_votes":[[0,2,2]],"_children":[{"_id":105839,"B":"pg","_mtype":0,"_contins":9,"_lock":0,"_metalock":0,"_alllangs":[]},{"_id":284112,"B":"nh","_mtype":0,"_contins":0,"_lock":0,"_metalock":0,"C":"Since White&#39;s shape is not so strong, this is a bit embarassing for White.","_lang":"en","_alllangs":["en"]}]}