{"_id":105906,"B":"tt","_mtype":0,"_contins":59,"_lock":0,"_metalock":0,"_alllangs":[],"_children":[{"_id":105907,"W":"mb","_mtype":0,"_contins":37,"_lock":0,"_metalock":0,"_alllangs":[]},{"_id":105939,"W":"re","_mtype":1,"_contins":11,"_lock":0,"_metalock":0,"_alllangs":[]},{"_id":105952,"W":"oc","_mtype":2,"_contins":1,"_lock":0,"_metalock":0,"C":"This defensive move should be played when black attacks white from [n14].","_lang":"en","_alllangs":["en"]},{"_id":176826,"W":"nc","_mtype":2,"_contins":6,"_lock":0,"_metalock":0,"_labels":[53],"_alllangs":[]}]}