{"_id":318533,"B":"qo","_mtype":0,"_contins":0,"_lock":0,"_metalock":0,"C":"\u00e6\u0153\u2039\u00e6\u2013\u017d\u00e6\u00b5\u0081","_lang":"ja","_alllangs":["ja"],"_children":[{"_id":619732,"W":"cf","_mtype":0,"_contins":0,"_lock":0,"_metalock":0,"_alllangs":[]},{"_id":619733,"W":"cn","_mtype":0,"_contins":0,"_lock":0,"_metalock":0,"_alllangs":[]},{"_id":619734,"W":"fc","_mtype":0,"_contins":0,"_lock":0,"_metalock":0,"_alllangs":[]},{"_id":619735,"W":"fq","_mtype":0,"_contins":0,"_lock":0,"_metalock":0,"_alllangs":[]}]}